finddd-0.2.1.dist-info/METADATA
finddd-0.2.1.dist-info/WHEEL
finddd/__init__.py
finddd/const.py
finddd/find.py
finddd/match.py
finddd/py.typed
finddd/test_find.py
finddd/test_match.py
finddd-0.2.1.dist-info/RECORD
