Metadata-Version: 2.1
Name: finddd
Version: 0.2.1
Author-Email: ayasechan <529157057@qq.com>
License: MIT
Requires-Python: >=3.8
Requires-Dist: igittigitt>=2.1.2
